pictex/__init__.py
pictex/__skia_init.py
pictex/bitmap_image.py
pictex/exceptions.py
pictex/py.typed
pictex/vector_image.py
pictex/builders/__init__.py
pictex/builders/canvas.py
pictex/builders/column.py
pictex/builders/container.py
pictex/builders/element.py
pictex/builders/image.py
pictex/builders/row.py
pictex/builders/stylable.py
pictex/builders/text.py
pictex/builders/with_position_mixin.py
pictex/builders/with_size_mixin.py
pictex/fonts/InterVariable.ttf
pictex/layout/__init__.py
pictex/layout/layout_engine.py
pictex/layout/layout_result.py
pictex/layout/style_mapper.py
pictex/models/__init__.py
pictex/models/internal/__init__.py
pictex/models/internal/render.py
pictex/models/internal/text.py
pictex/models/internal/typeface.py
pictex/models/public/__init__.py
pictex/models/public/background.py
pictex/models/public/border.py
pictex/models/public/box.py
pictex/models/public/color.py
pictex/models/public/crop.py
pictex/models/public/decoration.py
pictex/models/public/effects.py
pictex/models/public/layout.py
pictex/models/public/linear_gradient.py
pictex/models/public/node_type.py
pictex/models/public/paint_source.py
pictex/models/public/position.py
pictex/models/public/radial_gradient.py
pictex/models/public/render_node.py
pictex/models/public/size.py
pictex/models/public/style.py
pictex/models/public/style_property.py
pictex/models/public/sweep_gradient.py
pictex/models/public/transform.py
pictex/models/public/two_point_conical_gradient.py
pictex/models/public/typography.py
pictex/nodes/__init__.py
pictex/nodes/column_node.py
pictex/nodes/container_node.py
pictex/nodes/image_node.py
pictex/nodes/node.py
pictex/nodes/row_node.py
pictex/nodes/text_node.py
pictex/painters/__init__.py
pictex/painters/background.py
pictex/painters/border.py
pictex/painters/painter.py
pictex/painters/text.py
pictex/painters/text_decoration.py
pictex/renderer/__init__.py
pictex/renderer/image_processor.py
pictex/renderer/renderer.py
pictex/renderer/vector_image_processor.py
pictex-2.0.1.dist-info/METADATA
pictex-2.0.1.dist-info/WHEEL
pictex-2.0.1.dist-info/licenses/LICENSE
pictex-2.0.1.dist-info/RECORD
