Metadata-Version: 2.4
Name: pictex
Version: 2.0.1
Summary: A Python library for efficient image generation using CSS Flexbox.
Project-URL: Homepage, https://github.com/francozanardi/pictex
Project-URL: Repository, https://github.com/francozanardi/pictex
Project-URL: Issues, https://github.com/francozanardi/pictex/issues
Project-URL: Changelog, https://github.com/francozanardi/pictex/releases
Author-email: Franco Zanardi <francozanardi97@gmail.com>
License-File: LICENSE
Keywords: graphics,image-generation,skia,text-rendering,text-to-image,typography
Classifier: Development Status :: 4 - Beta
Classifier: Intended Audience :: Developers
Classifier: License :: OSI Approved :: MIT License
Classifier: Natural Language :: English
Classifier: Operating System :: OS Independent
Classifier: Programming Language :: Python :: 3
Classifier: Programming Language :: Python :: 3.9
Classifier: Programming Language :: Python :: 3.10
Classifier: Programming Language :: Python :: 3.11
Classifier: Programming Language :: Python :: 3.12
Classifier: Programming Language :: Python :: 3.13
Classifier: Topic :: Multimedia :: Graphics
Classifier: Topic :: Scientific/Engineering :: Visualization
Classifier: Topic :: Software Development :: Libraries :: Python Modules
Classifier: Topic :: Text Processing :: Fonts
Classifier: Typing :: Typed
Requires-Python: >=3.9
Requires-Dist: importlib-resources>=5.0; python_version < '3.10'
Requires-Dist: regex
Requires-Dist: skia-python
Requires-Dist: stretchable>=0.3.0
Requires-Dist: typing-extensions>=4.0; python_version < '3.11'
Provides-Extra: docs
Requires-Dist: mkdocs; extra == 'docs'
Requires-Dist: mkdocs-material; extra == 'docs'
Requires-Dist: mkdocstrings[python]; extra == 'docs'
Provides-Extra: test
Requires-Dist: mypy; extra == 'test'
Requires-Dist: pillow; extra == 'test'
Requires-Dist: pytest; extra == 'test'
Requires-Dist: pytest-cov; extra == 'test'
Requires-Dist: pytest-regressions; extra == 'test'
